Metadata-Version: 1.0
Name: pydap.handlers.csv
Version: 0.1.1
Summary: A CSV handler for Pydap
Home-page: http://pydap.org/handlers.html#csv
Author: Roberto De Almeida
Author-email: rob@pydap.org
License: MIT
Keywords: csv database opendap dods dap data science climate oceanography meteorology
Platform: UNKNOWN
Classifier: Development Status :: 5 - Production/Stable
Classifier: Environment :: Console
Classifier: Environment :: Web Environment
Classifier: Framework :: Paste
Classifier: Intended Audience :: Developers
Classifier: Intended Audience :: Science/Research
Classifier: License :: OSI Approved :: MIT License
Classifier: Operating System :: OS Independent
Classifier: Programming Language :: Python
Classifier: Topic :: Internet
Classifier: Topic :: Internet :: WWW/HTTP :: WSGI
Classifier: Topic :: Scientific/Engineering
Classifier: Topic :: Software Development :: Libraries :: Python Modules
